common/__init__.py
common/helloworld.py
helloworldpackage_python_test-0.0.1.dist-info/LICENSE
helloworldpackage_python_test-0.0.1.dist-info/METADATA
helloworldpackage_python_test-0.0.1.dist-info/WHEEL
helloworldpackage_python_test-0.0.1.dist-info/top_level.txt
helloworldpackage_python_test-0.0.1.dist-info/RECORD
