Metadata-Version: 2.1
Name: helloworldpackage-python-test
Version: 0.0.1
Summary: A simple package to print Hello, World!
Home-page: https://github.com/abhishek.maurya/helloworldpackage
Author: Abhishek Maurya
Author-email: abhishek.maurya@netcorecloud.com
License: UNKNOWN
Platform: UNKNOWN
Classifier: Programming Language :: Python :: 3
Classifier: License :: OSI Approved :: MIT License
Classifier: Operating System :: OS Independent
Requires-Python: >=3.6
License-File: LICENSE
